pythink_toolbox/__init__.py
pythink_toolbox/py.typed
pythink_toolbox/testing/__init__.py
pythink_toolbox/testing/mocking.py
pythink_toolbox/testing/parametrization.py
pythink_toolbox/testing/search_strategies.py
pythink_toolbox/validating.py
pythink_toolbox-1.2.0.dist-info/entry_points.txt
pythink_toolbox-1.2.0.dist-info/WHEEL
pythink_toolbox-1.2.0.dist-info/METADATA
pythink_toolbox-1.2.0.dist-info/RECORD
