Metadata-Version: 2.1
Name: pythink-toolbox
Version: 1.2.0
Summary: TODO
Requires-Python: >=3.8,<4.0
Classifier: Programming Language :: Python :: 3
Classifier: Programming Language :: Python :: 3.8
Classifier: Programming Language :: Python :: 3.9
Requires-Dist: pandera (>=0.4.4,<0.7.0)
